my_June_Package_Test/__init__.py
my_June_Package_Test/module1.py
tests/__init__.py
tests/test_module1.py
my_June_Package_Test-0.1.0.dist-info/LICENSE
my_June_Package_Test-0.1.0.dist-info/METADATA
my_June_Package_Test-0.1.0.dist-info/WHEEL
my_June_Package_Test-0.1.0.dist-info/top_level.txt
my_June_Package_Test-0.1.0.dist-info/RECORD
