Metadata-Version: 2.1
Name: my-June-Package-Test
Version: 0.1.0
Summary: A brief description of your package
Author: Akash
Author-email: your.email@example.com
Classifier: Programming Language :: Python :: 3
Classifier: License :: OSI Approved :: MIT License
Classifier: Operating System :: OS Independent
Requires-Python: >=3.6
License-File: LICENSE
